metop/__init__.py
metop/__main__.py
metop/models.py
metop/collectors/__init__.py
metop/collectors/ane.py
metop/collectors/gpu.py
metop/collectors/memory.py
metop/collectors/system.py
metop/tui/__init__.py
metop/tui/app.py
metop-0.1.1.dist-info/licenses/LICENSE
metop-0.1.1.dist-info/METADATA
metop-0.1.1.dist-info/WHEEL
metop-0.1.1.dist-info/entry_points.txt
metop-0.1.1.dist-info/top_level.txt
metop-0.1.1.dist-info/RECORD
