Metadata-Version: 2.4
Name: metop
Version: 0.1.1
Summary: macOS GPU/ANE Monitor for Apple Silicon
Author: metop contributors
License: MIT
Project-URL: Homepage, https://github.com/FanBB2333/metop
Project-URL: Documentation, https://github.com/FanBB2333/metop#readme
Project-URL: Repository, https://github.com/FanBB2333/metop
Project-URL: Issues, https://github.com/FanBB2333/metop/issues
Keywords: macos,gpu,ane,metal,mps,monitor,apple-silicon,m1,m2,m3
Classifier: Development Status :: 3 - Alpha
Classifier: Environment :: Console
Classifier: Intended Audience :: Developers
Classifier: License :: OSI Approved :: MIT License
Classifier: Operating System :: MacOS :: MacOS X
Classifier: Programming Language :: Python :: 3
Classifier: Programming Language :: Python :: 3.9
Classifier: Programming Language :: Python :: 3.10
Classifier: Programming Language :: Python :: 3.11
Classifier: Programming Language :: Python :: 3.12
Classifier: Topic :: System :: Monitoring
Classifier: Topic :: Scientific/Engineering :: Artificial Intelligence
Requires-Python: >=3.9
License-File: LICENSE
Requires-Dist: rich>=13.0.0
Requires-Dist: psutil>=5.9.0
Provides-Extra: fast
Requires-Dist: pyobjc-framework-Cocoa>=9.0; extra == "fast"
Provides-Extra: dev
Requires-Dist: pytest>=7.0.0; extra == "dev"
Requires-Dist: pytest-cov>=4.0.0; extra == "dev"
Requires-Dist: black>=23.0.0; extra == "dev"
Requires-Dist: ruff>=0.1.0; extra == "dev"
Dynamic: license-file
